{
  "FilePath": "c:\\Users\\GAMER\\Desktop\\Curso\\b808a33f-71ee-47de-91a3-be34b9637cf6\\aurora-api-project-master\\Aurora.Application\\Aurora.Application.csproj",
  "Configuration": {
    "ConfigurationName": "MVC-3.0",
    "LanguageVersion": "3.0",
    "Extensions": [
      {
        "ExtensionName": "MVC-3.0"
      }
    ]
  },
  "ProjectWorkspaceState": {
    "TagHelpers": [],
    "CSharpLanguageVersion": 800
  },
  "RootNamespace": "Aurora.Application",
  "Documents": [],
  "SerializationFormat": "0.2"
}